eclients/__init__.py
eclients/db_client.py
eclients/decorators.py
eclients/err_msg.py
eclients/exceptions.py
eclients/http_client.py
eclients/mongo_client.py
eclients/redis_client.py
eclients/utils.py
eclients/jsonrpc/__init__.py
eclients/jsonrpc/jrpc_client.py
eclients/jsonrpc/jrpc_server.py
eclients/tinylibs/__init__.py
eclients/tinylibs/tinymysql.py
eclients-1.0.12.dist-info/LICENSE
eclients-1.0.12.dist-info/METADATA
eclients-1.0.12.dist-info/WHEEL
eclients-1.0.12.dist-info/top_level.txt
eclients-1.0.12.dist-info/RECORD
