Metadata-Version: 2.1
Name: eclients
Version: 1.0.12
Summary: 基础封装库
Home-page: https://github.com/tinybees/eclients
Author: TinyBees
Author-email: a598824322@qq.com
License: MIT
Keywords: mongo,redis,http,crud,session
Platform: UNKNOWN
Classifier: Development Status :: 4 - Beta
Classifier: Intended Audience :: Developers
Classifier: License :: OSI Approved :: MIT License
Classifier: Natural Language :: Chinese (Simplified)
Classifier: Operating System :: POSIX :: Linux
Classifier: Operating System :: Microsoft :: Windows
Classifier: Operating System :: MacOS :: MacOS X
Classifier: Topic :: Software Development :: Libraries :: Python Modules
Classifier: Topic :: Utilities
Classifier: Programming Language :: Python
Classifier: Programming Language :: Python :: 3.5
Classifier: Programming Language :: Python :: 3.6
Classifier: Programming Language :: Python :: 3.7
Requires-Python: >=3.5
Requires-Dist: aelog (>=1.0.3)
Requires-Dist: pymongo (>=3.8.0)
Requires-Dist: requests (>=2.21.0)
Requires-Dist: marshmallow (>=3.0.0rc3)
Requires-Dist: ujson
Requires-Dist: flask (>=1.0.2)
Requires-Dist: sqlalchemy (<=1.3.23,>=1.2.12)
Requires-Dist: flask-sqlalchemy (>=2.3.2)
Requires-Dist: redis (>=3.0.0)
Requires-Dist: pymysql (>=0.9.2)
Requires-Dist: PyYAML (>=3.13)
Requires-Dist: boltons (>=18.0.1)
